view_df/__init__.py
view_df/main.py
view_df-0.2.8.dist-info/LICENSE.txt
view_df-0.2.8.dist-info/METADATA
view_df-0.2.8.dist-info/WHEEL
view_df-0.2.8.dist-info/top_level.txt
view_df-0.2.8.dist-info/RECORD
