Metadata-Version: 2.1
Name: view-df
Version: 0.2.8
Summary: A Python module to display large pandas DataFrames with auto-adjusted column widths in a web browser with filtering capability.
Author: Arslaan Kola
Author-email: kolaarslaan[at]gmail[dot]com
License-File: LICENSE.txt
